simple-feature-selection/__init__.py
simple-feature-selection/simple_feature_selection.py
simplefeatureselection/__init__.py
simplefeatureselection/simplefeatureselection.py
simplefeatureselection-0.0.2.dist-info/METADATA
simplefeatureselection-0.0.2.dist-info/WHEEL
simplefeatureselection-0.0.2.dist-info/top_level.txt
simplefeatureselection-0.0.2.dist-info/RECORD
