Metadata-Version: 2.1
Name: simplefeatureselection
Version: 0.0.2
Summary: Simple Tab Feature Selection
Home-page: https://github.com/fukasawat78/simple-feature-selection
Author: fukasawat
Author-email: tatsuya.fukasawa1024@gmail.com
License: MIT
Keywords: feature selection,feature engineering,tabular data
Platform: UNKNOWN
Classifier: Development Status :: 4 - Beta
Classifier: Intended Audience :: Developers
Classifier: Topic :: Scientific/Engineering :: Artificial Intelligence
Classifier: License :: OSI Approved :: MIT License
Classifier: Programming Language :: Python :: 3.7
Requires-Dist: category-encoders (>=2.2.2)
Requires-Dist: scikit-learn (>=0.23.2)
Requires-Dist: Boruta (>=0.3)
